{"data": {"CoinGecko": {"BTC": 27315, "ADA": 0.381575, "LTC": 95.7, "ETH": 1908.53, "USDT": 0.999142}, "CoinLayer": {"ADA": 0.382541, "BTC": 27302.20768, "ETH": 1911.364875, "LTC": 95.882588, "USDT": 1.005502}, "Binance": {"BTC": 27321.57, "ETH": 1907.06, "LTC": 95.63, "USDT": 1.0006, "ADA": 0.3813}, "Livecoin": {"BTC": 27353.583679135034, "ETH": 1909.031877377659, "USDT": 1.0006301707956944, "ADA": 0.38155972276161015, "LTC": 95.63817457032874}}, "ops": [{"coin": {"name": "BTC", "link": "https://coinmarketcap.com/currencies/bitcoin/"}, "sellerMarket": {"name": "CoinLayer", "link": "https://coinlayer.com/"}, "buyPrice": 27302.20768, "buyerMarket": {"name": "CoinGecko", "link": "https://www.coingecko.com/"}, "sellPrice": 27315}, {"coin": {"name": "BTC", "link": "https://coinmarketcap.com/currencies/bitcoin/"}, "sellerMarket": {"name": "CoinGecko", "link": "https://www.coingecko.com/"}, "buyPrice": 27315, "buyerMarket": {"name": "Binance", "link": "https://www.binance.com/en"}, "sellPrice": 27321.57}, {"coin": {"name": "BTC", "link": "https://coinmarketcap.com/currencies/bitcoin/"}, "sellerMarket": {"name": "CoinGecko", "link": "https://www.coingecko.com/"}, "buyPrice": 27315, "buyerMarket": {"name": "Livecoin", "link": "https://www.livecoinwatch.com/"}, "sellPrice": 27353.583679135034}, {"coin": {"name": "BTC", "link": "https://coinmarketcap.com/currencies/bitcoin/"}, "sellerMarket": {"name": "CoinLayer", "link": "https://coinlayer.com/"}, "buyPrice": 27302.20768, "buyerMarket": {"name": "Binance", "link": "https://www.binance.com/en"}, "sellPrice": 27321.57}, {"coin": {"name": "BTC", "link": "https://coinmarketcap.com/currencies/bitcoin/"}, "sellerMarket": {"name": "CoinLayer", "link": "https://coinlayer.com/"}, "buyPrice": 27302.20768, "buyerMarket": {"name": "Livecoin", "link": "https://www.livecoinwatch.com/"}, "sellPrice": 27353.583679135034}, {"coin": {"name": "BTC", "link": "https://coinmarketcap.com/currencies/bitcoin/"}, "sellerMarket": {"name": "Binance", "link": "https://www.binance.com/en"}, "buyPrice": 27321.57, "buyerMarket": {"name": "Livecoin", "link": "https://www.livecoinwatch.com/"}, "sellPrice": 27353.583679135034}, {"coin": {"name": "LTC", "link": "https://coinmarketcap.com/currencies/litecoin/"}, "sellerMarket": {"name": "CoinGecko", "link": "https://www.coingecko.com/"}, "buyPrice": 95.7, "buyerMarket": {"name": "CoinLayer", "link": "https://coinlayer.com/"}, "sellPrice": 95.882588}, {"coin": {"name": "LTC", "link": "https://coinmarketcap.com/currencies/litecoin/"}, "sellerMarket": {"name": "Binance", "link": "https://www.binance.com/en"}, "buyPrice": 95.63, "buyerMarket": {"name": "CoinGecko", "link": "https://www.coingecko.com/"}, "sellPrice": 95.7}, {"coin": {"name": "LTC", "link": "https://coinmarketcap.com/currencies/litecoin/"}, "sellerMarket": {"name": "Livecoin", "link": "https://www.livecoinwatch.com/"}, "buyPrice": 95.63817457032874, "buyerMarket": {"name": "CoinGecko", "link": "https://www.coingecko.com/"}, "sellPrice": 95.7}, {"coin": {"name": "LTC", "link": "https://coinmarketcap.com/currencies/litecoin/"}, "sellerMarket": {"name": "Binance", "link": "https://www.binance.com/en"}, "buyPrice": 95.63, "buyerMarket": {"name": "CoinLayer", "link": "https://coinlayer.com/"}, "sellPrice": 95.882588}, {"coin": {"name": "LTC", "link": "https://coinmarketcap.com/currencies/litecoin/"}, "sellerMarket": {"name": "Livecoin", "link": "https://www.livecoinwatch.com/"}, "buyPrice": 95.63817457032874, "buyerMarket": {"name": "CoinLayer", "link": "https://coinlayer.com/"}, "sellPrice": 95.882588}, {"coin": {"name": "LTC", "link": "https://coinmarketcap.com/currencies/litecoin/"}, "sellerMarket": {"name": "Binance", "link": "https://www.binance.com/en"}, "buyPrice": 95.63, "buyerMarket": {"name": "Livecoin", "link": "https://www.livecoinwatch.com/"}, "sellPrice": 95.63817457032874}, {"coin": {"name": "ETH", "link": "https://coinmarketcap.com/currencies/ethereum/"}, "sellerMarket": {"name": "CoinGecko", "link": "https://www.coingecko.com/"}, "buyPrice": 1908.53, "buyerMarket": {"name": "CoinLayer", "link": "https://coinlayer.com/"}, "sellPrice": 1911.364875}, {"coin": {"name": "ETH", "link": "https://coinmarketcap.com/currencies/ethereum/"}, "sellerMarket": {"name": "Binance", "link": "https://www.binance.com/en"}, "buyPrice": 1907.06, "buyerMarket": {"name": "CoinGecko", "link": "https://www.coingecko.com/"}, "sellPrice": 1908.53}, {"coin": {"name": "ETH", "link": "https://coinmarketcap.com/currencies/ethereum/"}, "sellerMarket": {"name": "CoinGecko", "link": "https://www.coingecko.com/"}, "buyPrice": 1908.53, "buyerMarket": {"name": "Livecoin", "link": "https://www.livecoinwatch.com/"}, "sellPrice": 1909.031877377659}, {"coin": {"name": "ETH", "link": "https://coinmarketcap.com/currencies/ethereum/"}, "sellerMarket": {"name": "Binance", "link": "https://www.binance.com/en"}, "buyPrice": 1907.06, "buyerMarket": {"name": "CoinLayer", "link": "https://coinlayer.com/"}, "sellPrice": 1911.364875}, {"coin": {"name": "ETH", "link": "https://coinmarketcap.com/currencies/ethereum/"}, "sellerMarket": {"name": "Livecoin", "link": "https://www.livecoinwatch.com/"}, "buyPrice": 1909.031877377659, "buyerMarket": {"name": "CoinLayer", "link": "https://coinlayer.com/"}, "sellPrice": 1911.364875}, {"coin": {"name": "ETH", "link": "https://coinmarketcap.com/currencies/ethereum/"}, "sellerMarket": {"name": "Binance", "link": "https://www.binance.com/en"}, "buyPrice": 1907.06, "buyerMarket": {"name": "Livecoin", "link": "https://www.livecoinwatch.com/"}, "sellPrice": 1909.031877377659}, {"coin": {"name": "ADA", "link": "https://coinmarketcap.com/currencies/cardano/"}, "sellerMarket": {"name": "CoinGecko", "link": "https://www.coingecko.com/"}, "buyPrice": 0.381575, "buyerMarket": {"name": "CoinLayer", "link": "https://coinlayer.com/"}, "sellPrice": 0.382541}, {"coin": {"name": "ADA", "link": "https://coinmarketcap.com/currencies/cardano/"}, "sellerMarket": {"name": "Binance", "link": "https://www.binance.com/en"}, "buyPrice": 0.3813, "buyerMarket": {"name": "CoinGecko", "link": "https://www.coingecko.com/"}, "sellPrice": 0.381575}, {"coin": {"name": "ADA", "link": "https://coinmarketcap.com/currencies/cardano/"}, "sellerMarket": {"name": "Livecoin", "link": "https://www.livecoinwatch.com/"}, "buyPrice": 0.38155972276161015, "buyerMarket": {"name": "CoinGecko", "link": "https://www.coingecko.com/"}, "sellPrice": 0.381575}, {"coin": {"name": "ADA", "link": "https://coinmarketcap.com/currencies/cardano/"}, "sellerMarket": {"name": "Binance", "link": "https://www.binance.com/en"}, "buyPrice": 0.3813, "buyerMarket": {"name": "CoinLayer", "link": "https://coinlayer.com/"}, "sellPrice": 0.382541}, {"coin": {"name": "ADA", "link": "https://coinmarketcap.com/currencies/cardano/"}, "sellerMarket": {"name": "Livecoin", "link": "https://www.livecoinwatch.com/"}, "buyPrice": 0.38155972276161015, "buyerMarket": {"name": "CoinLayer", "link": "https://coinlayer.com/"}, "sellPrice": 0.382541}, {"coin": {"name": "ADA", "link": "https://coinmarketcap.com/currencies/cardano/"}, "sellerMarket": {"name": "Binance", "link": "https://www.binance.com/en"}, "buyPrice": 0.3813, "buyerMarket": {"name": "Livecoin", "link": "https://www.livecoinwatch.com/"}, "sellPrice": 0.38155972276161015}, {"coin": {"name": "USDT", "link": "https://coinmarketcap.com/currencies/tether/"}, "sellerMarket": {"name": "CoinGecko", "link": "https://www.coingecko.com/"}, "buyPrice": 0.999142, "buyerMarket": {"name": "CoinLayer", "link": "https://coinlayer.com/"}, "sellPrice": 1.005502}, {"coin": {"name": "USDT", "link": "https://coinmarketcap.com/currencies/tether/"}, "sellerMarket": {"name": "CoinGecko", "link": "https://www.coingecko.com/"}, "buyPrice": 0.999142, "buyerMarket": {"name": "Binance", "link": "https://www.binance.com/en"}, "sellPrice": 1.0006}, {"coin": {"name": "USDT", "link": "https://coinmarketcap.com/currencies/tether/"}, "sellerMarket": {"name": "CoinGecko", "link": "https://www.coingecko.com/"}, "buyPrice": 0.999142, "buyerMarket": {"name": "Livecoin", "link": "https://www.livecoinwatch.com/"}, "sellPrice": 1.0006301707956944}, {"coin": {"name": "USDT", "link": "https://coinmarketcap.com/currencies/tether/"}, "sellerMarket": {"name": "Binance", "link": "https://www.binance.com/en"}, "buyPrice": 1.0006, "buyerMarket": {"name": "CoinLayer", "link": "https://coinlayer.com/"}, "sellPrice": 1.005502}, {"coin": {"name": "USDT", "link": "https://coinmarketcap.com/currencies/tether/"}, "sellerMarket": {"name": "Livecoin", "link": "https://www.livecoinwatch.com/"}, "buyPrice": 1.0006301707956944, "buyerMarket": {"name": "CoinLayer", "link": "https://coinlayer.com/"}, "sellPrice": 1.005502}, {"coin": {"name": "USDT", "link": "https://coinmarketcap.com/currencies/tether/"}, "sellerMarket": {"name": "Binance", "link": "https://www.binance.com/en"}, "buyPrice": 1.0006, "buyerMarket": {"name": "Livecoin", "link": "https://www.livecoinwatch.com/"}, "sellPrice": 1.0006301707956944}], "yester": {"ADA": {"Open": [0.377055], "High": [0.3855], "Low": [0.37314], "Close": [0.377055], "Adj Close": [0.377055], "Volume": [25903145.737566], "year": [2023], "month": [6], "day": [3]}, "BTC": {"Open": [27154.25942], "High": [27976.99], "Low": [26922.88], "Close": [27154.25942], "Adj Close": [27154.25942], "Volume": [990697900.52922], "year": [2023], "month": [6], "day": [3]}, "ETH": {"Open": [1894.24637], "High": [1955], "Low": [1864.21], "Close": [1894.24637], "Adj Close": [1894.24637], "Volume": [673339863.836623], "year": [2023], "month": [6], "day": [3]}, "LTC": {"Open": [96.228143], "High": [101.9], "Low": [94.142], "Close": [96.228143], "Adj Close": [96.228143], "Volume": [136254086.110816], "year": [2023], "month": [6], "day": [3]}, "USDT": {"Open": [1.00788], "High": [1.028], "Low": [1.000199], "Close": [1.00788], "Adj Close": [1.00788], "Volume": [159523818.259494], "year": [2023], "month": [6], "day": [3]}}, "pred_data": {"BTC": 27157.44860891944, "LTC": 96.8598901002432, "ETH": 1879.4094549479764, "ADA": 0.37865193029366706, "USDT": 1.0070953639916458}}